django_twilio/__init__.py
django_twilio/admin.py
django_twilio/client.py
django_twilio/decorators.py
django_twilio/exceptions.py
django_twilio/models.py
django_twilio/request.py
django_twilio/settings.py
django_twilio/utils.py
django_twilio/views.py
django_twilio/migrations/0001_initial.py
django_twilio/migrations/__init__.py
django_twilio/south_migrations/0001_initial.py
django_twilio/south_migrations/__init__.py
django_twilio2/__init__.py
django_twilio2/admin.py
django_twilio2/client.py
django_twilio2/decorators.py
django_twilio2/exceptions.py
django_twilio2/models.py
django_twilio2/request.py
django_twilio2/settings.py
django_twilio2/utils.py
django_twilio2/views.py
django_twilio2/migrations/0001_initial.py
django_twilio2/migrations/__init__.py
django_twilio2-0.9.0.dist-info/DESCRIPTION.rst
django_twilio2-0.9.0.dist-info/METADATA
django_twilio2-0.9.0.dist-info/RECORD
django_twilio2-0.9.0.dist-info/WHEEL
django_twilio2-0.9.0.dist-info/metadata.json
django_twilio2-0.9.0.dist-info/top_level.txt
test_project/__init__.py
test_project/settings.py
test_project/urls.py
test_project/test_app/__init__.py
test_project/test_app/client.py
test_project/test_app/decorators.py
test_project/test_app/models.py
test_project/test_app/request.py
test_project/test_app/urls.py
test_project/test_app/utils.py
test_project/test_app/views.py
